tweak/__init__.py
tweak-1.0.3.dist-info/LICENSE
tweak-1.0.3.dist-info/METADATA
tweak-1.0.3.dist-info/WHEEL
tweak-1.0.3.dist-info/top_level.txt
tweak-1.0.3.dist-info/RECORD
